setup.py
pbd_distribuciones/Binomialdistribution.py
pbd_distribuciones/Gaussiandistribution.py
pbd_distribuciones/Generaldistribution.py
pbd_distribuciones/__init__.py
pbd_distribuciones.egg-info/PKG-INFO
pbd_distribuciones.egg-info/SOURCES.txt
pbd_distribuciones.egg-info/dependency_links.txt
pbd_distribuciones.egg-info/not-zip-safe
pbd_distribuciones.egg-info/top_level.txt