Metadata-Version: 1.0
Name: pbd-distribuciones
Version: 1.0
Summary: Gaussian and Binomial distributions
Home-page: UNKNOWN
Author: Alejandrina Jimenez Guzman
Author-email: UNKNOWN
License: UNKNOWN
Platform: UNKNOWN
